LICENSE
README.md
setup.cfg
setup.py
akane/__init__.py
akane/assertions.py
akane/helpder.py
akane/procedures.py
akane.egg-info/PKG-INFO
akane.egg-info/SOURCES.txt
akane.egg-info/dependency_links.txt
akane.egg-info/requires.txt
akane.egg-info/top_level.txt