Metadata-Version: 2.1
Name: akane
Version: 1.0.0
Summary: Simple, stronly typed library to create tests for anything
Home-page: https://github.com/zekrotja/akane
Download-URL: https://github.com/zekrotja/akane/archive/main.tar.gz
Author: zekro
Author-email: contact@zekro.de
Classifier: Programming Language :: Python :: 3.10
Classifier: License :: OSI Approved :: MIT License
Classifier: Operating System :: OS Independent
Classifier: Topic :: Software Development :: Libraries
License-File: LICENSE
